odoo/addons/sale_operating_unit/README.rst
odoo/addons/sale_operating_unit/__init__.py
odoo/addons/sale_operating_unit/__manifest__.py
odoo/addons/sale_operating_unit/i18n/es.po
odoo/addons/sale_operating_unit/i18n/sale_operating_unit.pot
odoo/addons/sale_operating_unit/models/__init__.py
odoo/addons/sale_operating_unit/models/crm_team.py
odoo/addons/sale_operating_unit/models/sale_order.py
odoo/addons/sale_operating_unit/readme/CONTRIBUTORS.rst
odoo/addons/sale_operating_unit/readme/DESCRIPTION.rst
odoo/addons/sale_operating_unit/readme/USAGE.rst
odoo/addons/sale_operating_unit/report/__init__.py
odoo/addons/sale_operating_unit/report/sale_report.py
odoo/addons/sale_operating_unit/security/sale_security.xml
odoo/addons/sale_operating_unit/static/description/icon.png
odoo/addons/sale_operating_unit/static/description/index.html
odoo/addons/sale_operating_unit/tests/__init__.py
odoo/addons/sale_operating_unit/tests/test_sale_operating_unit.py
odoo/addons/sale_operating_unit/views/sale_report_view.xml
odoo/addons/sale_operating_unit/views/sale_view.xml
odoo/addons/sale_operating_unit/wizard/__init__.py
odoo/addons/sale_operating_unit/wizard/sale_make_invoice_advance.py
odoo13_addon_sale_operating_unit-13.0.1.1.0.dist-info/METADATA
odoo13_addon_sale_operating_unit-13.0.1.1.0.dist-info/WHEEL
odoo13_addon_sale_operating_unit-13.0.1.1.0.dist-info/top_level.txt
odoo13_addon_sale_operating_unit-13.0.1.1.0.dist-info/RECORD
